{
  "saved_at": 1781690964,
  "saved_at_iso": "2026-06-17T10:09:24.900543+00:00",
  "data": {
    "address": "1035580d667b7941bb55a5cf4ea5e6433d410aa3",
    "tx_count": "85",
    "type": 0,
    "balance": "5923291828618815971",
    "nonce": "84",
    "code_hash": null,
    "created_at_block": "33308775",
    "updated_at_block": "36346931",
    "token_count": 0,
    "nft_count": 2,
    "delegations_count": 0,
    "erc20_count": 0,
    "erc721_count": 2,
    "erc1155_count": 0,
    "labels": [],
    "public_tags": [],
    "private_tags": [],
    "watchlist_names": [],
    "name": null,
    "is_contract": false,
    "contract": null,
    "is_token": false,
    "token": null,
    "has_tokens": true,
    "has_token_transfers": true,
    "has_logs": false,
    "has_validated_blocks": false,
    "has_internal_transactions": true,
    "internal_transactions_count": 84,
    "has_transactions": true,
    "source": "db"
  }
}