{
  "saved_at": 1781893449,
  "saved_at_iso": "2026-06-19T18:24:09.249100+00:00",
  "data": {
    "address": "a001b52f44c6fed90fda3744a7e8668b52265adc",
    "tx_count": "8638",
    "type": 0,
    "balance": "1445192330713989466",
    "nonce": "8632",
    "code_hash": null,
    "created_at_block": "34480393",
    "updated_at_block": "36497420",
    "token_count": 0,
    "nft_count": 3,
    "delegations_count": 0,
    "erc20_count": 0,
    "erc721_count": 3,
    "erc1155_count": 0,
    "labels": [],
    "public_tags": [],
    "private_tags": [],
    "watchlist_names": [],
    "name": null,
    "is_contract": false,
    "contract": null,
    "is_token": false,
    "token": null,
    "has_tokens": true,
    "has_token_transfers": true,
    "has_logs": false,
    "has_validated_blocks": false,
    "has_internal_transactions": true,
    "internal_transactions_count": 2525,
    "has_transactions": true,
    "source": "db"
  }
}