{
  "saved_at": 1781799734,
  "saved_at_iso": "2026-06-18T16:22:14.042526+00:00",
  "data": {
    "address": "105252e53500a8885c048d3dc86b046a5809b32b",
    "tx_count": "14",
    "type": 0,
    "balance": "330801175999994",
    "nonce": "8",
    "code_hash": null,
    "created_at_block": "35060214",
    "updated_at_block": "36101746",
    "token_count": 0,
    "nft_count": 2,
    "delegations_count": 0,
    "erc20_count": 0,
    "erc721_count": 2,
    "erc1155_count": 0,
    "labels": [],
    "public_tags": [],
    "private_tags": [],
    "watchlist_names": [],
    "name": null,
    "is_contract": false,
    "contract": null,
    "is_token": false,
    "token": null,
    "has_tokens": true,
    "has_token_transfers": true,
    "has_logs": false,
    "has_validated_blocks": false,
    "has_internal_transactions": false,
    "internal_transactions_count": 0,
    "has_transactions": true,
    "source": "db"
  }
}