[
  {
    "rank": 1,
    "address": "0x9935eaa74e7bfa87d50d51df8646965816676b76",
    "points": 244660,
    "tx": 23003,
    "sbt": "OVZ",
    "time": "2026-06-22T12:57:57.617533+00:00"
  },
  {
    "rank": 2,
    "address": "0xaf0fddcd716950cbfa5c0678a294e00870ea31e6",
    "points": 242750,
    "tx": 13530,
    "sbt": "OV",
    "time": "2026-06-22T12:57:57.617554+00:00"
  },
  {
    "rank": 3,
    "address": "0x6b6381f2cad74d84c5822aeb5e2a22912d8b5105",
    "points": 225990,
    "tx": 17748,
    "sbt": "OV",
    "time": "2026-06-22T12:57:57.617564+00:00"
  },
  {
    "rank": 4,
    "address": "0x10d493cd7aa810a2aff0095de8b288180affd4f1",
    "points": 223010,
    "tx": 26379,
    "sbt": "OV",
    "time": "2026-06-22T12:57:57.617573+00:00"
  },
  {
    "rank": 5,
    "address": "0x4e546dc8500060f439e2011727950879400c1e64",
    "points": 205370,
    "tx": 23602,
    "sbt": "OV",
    "time": "2026-06-22T12:57:57.617580+00:00"
  },
  {
    "rank": 6,
    "address": "0x22a5212d9de8f2670839462a92cb1cd81060f8d9",
    "points": 203680,
    "tx": 28322,
    "sbt": "OV",
    "time": "2026-06-22T12:57:57.617589+00:00"
  },
  {
    "rank": 7,
    "address": "0xc47f5372eddc289e2da9b04a9b97bc898dae9688",
    "points": 185420,
    "tx": 17515,
    "sbt": "OVZ",
    "time": "2026-06-22T12:57:57.617597+00:00"
  },
  {
    "rank": 8,
    "address": "0xb5e058b1d5bdeecba58cc4fd7c38f0156e52d2d2",
    "points": 179090,
    "tx": 15909,
    "sbt": "OVZ",
    "time": "2026-06-22T12:57:57.617605+00:00"
  },
  {
    "rank": 9,
    "address": "0x7c8e91ec5a580189123d0dca042764343b35e3ad",
    "points": 168870,
    "tx": 26840,
    "sbt": "OV",
    "time": "2026-06-22T12:57:57.617613+00:00"
  },
  {
    "rank": 10,
    "address": "0xb6ac59d4d602f6cc6de8e15eae3c1b84eddf7de5",
    "points": 168330,
    "tx": 14927,
    "sbt": "OV",
    "time": "2026-06-22T12:57:57.617622+00:00"
  },
  {
    "rank": 11,
    "address": "0x8182537b563c6e0dc9e1f7f79d09ac64f2e1ee3b",
    "points": 165320,
    "tx": 9363,
    "sbt": "OV",
    "time": "2026-06-22T12:57:57.617630+00:00"
  },
  {
    "rank": 12,
    "address": "0xeb3ab854e5923464f67967d9fdec4bd1c0da466d",
    "points": 164500,
    "tx": 19315,
    "sbt": "OV",
    "time": "2026-06-22T12:57:57.617637+00:00"
  },
  {
    "rank": 13,
    "address": "0x8665e262680a6fb6cf51553ef282cc20a3337332",
    "points": 153790,
    "tx": 13248,
    "sbt": "OV",
    "time": "2026-06-22T12:57:57.617644+00:00"
  },
  {
    "rank": 14,
    "address": "0xa8dab875eb73173c8c96215445263aa6a6851af6",
    "points": 150150,
    "tx": 18015,
    "sbt": "OVZ",
    "time": "2026-06-22T12:57:57.617652+00:00"
  },
  {
    "rank": 15,
    "address": "0x9fcb733c89f627f6da82724799c4275c8986cac7",
    "points": 146960,
    "tx": 12146,
    "sbt": "OV",
    "time": "2026-06-22T12:57:57.617660+00:00"
  },
  {
    "rank": 16,
    "address": "0x57e8207e2fa11396a625fc3558ecbac1cb011eed",
    "points": 103730,
    "tx": 9058,
    "sbt": "OV",
    "time": "2026-06-22T12:57:57.617667+00:00"
  },
  {
    "rank": 17,
    "address": "0x0b1ee41f0501478edbce72f21c9160edff46d0b7",
    "points": 83000,
    "tx": 20452,
    "sbt": "OV",
    "time": "2026-06-22T12:57:57.617676+00:00"
  },
  {
    "rank": 18,
    "address": "0x6a5464ac1ecb26042c41d66fbbd017355106ecd0",
    "points": 82560,
    "tx": 2485,
    "sbt": "OV",
    "time": "2026-06-22T12:57:57.617684+00:00"
  },
  {
    "rank": 19,
    "address": "0x5bd511fdf28c1c873e3d508b9bb5145d5350ee7b",
    "points": 82540,
    "tx": 12487,
    "sbt": "OVZ",
    "time": "2026-06-22T12:57:57.617691+00:00"
  },
  {
    "rank": 20,
    "address": "0xe4a8cf8c66a1f0fabc4d218eba947b5c20633c12",
    "points": 82310,
    "tx": 2440,
    "sbt": "OV",
    "time": "2026-06-22T12:57:57.617698+00:00"
  },
  {
    "rank": 21,
    "address": "0x905c4acf26e7a2fadf477f8d39b9aa3e02d85a1d",
    "points": 82260,
    "tx": 2454,
    "sbt": "OV",
    "time": "2026-06-22T12:57:57.617706+00:00"
  },
  {
    "rank": 22,
    "address": "0xe6706a4fca1374b514cf22d855d9d8cfe16421cc",
    "points": 67500,
    "tx": 11159,
    "sbt": "-",
    "time": "2026-06-22T12:57:57.617714+00:00"
  },
  {
    "rank": 23,
    "address": "0xf364436e369f7d14ef7e09391b3ab35e05aeb679",
    "points": 66810,
    "tx": 9761,
    "sbt": "OV",
    "time": "2026-06-22T12:57:57.617722+00:00"
  },
  {
    "rank": 24,
    "address": "0x5f58714cd514885a2dd2438e89e1c32ee4945324",
    "points": 63670,
    "tx": 8185,
    "sbt": "-",
    "time": "2026-06-22T12:57:57.617729+00:00"
  },
  {
    "rank": 25,
    "address": "0x70b4a3f5deed9f8147860da9d21fe8580139d3e0",
    "points": 62910,
    "tx": 9921,
    "sbt": "OV",
    "time": "2026-06-22T12:57:57.617737+00:00"
  },
  {
    "rank": 26,
    "address": "0x462b50df6b85450d2e0ba5c47298c198ed30f9cb",
    "points": 62300,
    "tx": 2451,
    "sbt": "-",
    "time": "2026-06-22T12:57:57.617746+00:00"
  },
  {
    "rank": 27,
    "address": "0x715d4eb4a21e2e50f4f0083e3c05d1042b8fac05",
    "points": 61930,
    "tx": 5510,
    "sbt": "OVZ",
    "time": "2026-06-22T12:57:57.617754+00:00"
  },
  {
    "rank": 28,
    "address": "0xcdfc916cd6aa6687a6eb26c365fe945697a2b5d0",
    "points": 61360,
    "tx": 2049,
    "sbt": "OV",
    "time": "2026-06-22T12:57:57.617762+00:00"
  },
  {
    "rank": 29,
    "address": "0x3e7f688a972e9254bfa0f866d4aa3fc946f4affa",
    "points": 60700,
    "tx": 2554,
    "sbt": "-",
    "time": "2026-06-22T12:57:57.617808+00:00"
  },
  {
    "rank": 30,
    "address": "0xff062ae44ef8863f375b957661caf19cc2749e3e",
    "points": 59800,
    "tx": 2502,
    "sbt": "-",
    "time": "2026-06-22T12:57:57.617817+00:00"
  },
  {
    "rank": 31,
    "address": "0x03e0295cb5d43a3bb1d0da1ad9b8ca36b21e05d0",
    "points": 59500,
    "tx": 2603,
    "sbt": "-",
    "time": "2026-06-22T12:57:57.617825+00:00"
  },
  {
    "rank": 32,
    "address": "0xfde4e22cfec60ab6cd32dc2bfcf435fb9b41dbd5",
    "points": 59450,
    "tx": 9515,
    "sbt": "OV",
    "time": "2026-06-22T12:57:57.617832+00:00"
  },
  {
    "rank": 33,
    "address": "0x34d04f1dca0c8f3cd6237275152d8fce9296f453",
    "points": 59350,
    "tx": 2550,
    "sbt": "-",
    "time": "2026-06-22T12:57:57.617839+00:00"
  },
  {
    "rank": 34,
    "address": "0xa898b5c88d756864adc980ba68527581298312ac",
    "points": 58750,
    "tx": 2582,
    "sbt": "-",
    "time": "2026-06-22T12:57:57.617847+00:00"
  },
  {
    "rank": 35,
    "address": "0x302d87d0bddee75f407d8029db833388e6b859fa",
    "points": 58050,
    "tx": 2551,
    "sbt": "-",
    "time": "2026-06-22T12:57:57.617854+00:00"
  },
  {
    "rank": 36,
    "address": "0x8204062cc3310f67abffc013d76b8880b869494e",
    "points": 58000,
    "tx": 2565,
    "sbt": "-",
    "time": "2026-06-22T12:57:57.617900+00:00"
  },
  {
    "rank": 37,
    "address": "0xfc8b53d2a7798a0fc9d5de96265a59757f9fee96",
    "points": 57850,
    "tx": 2608,
    "sbt": "-",
    "time": "2026-06-22T12:57:57.617908+00:00"
  },
  {
    "rank": 38,
    "address": "0x314c095b9e189033e08f9e3d9991c045bda5eeb2",
    "points": 57450,
    "tx": 2599,
    "sbt": "-",
    "time": "2026-06-22T12:57:57.617916+00:00"
  },
  {
    "rank": 39,
    "address": "0x5628144be22ba8051d1c65660718e58577d49f13",
    "points": 57350,
    "tx": 2592,
    "sbt": "-",
    "time": "2026-06-22T12:57:57.617925+00:00"
  },
  {
    "rank": 40,
    "address": "0xab766edc5c5560d9004e13debf11978d96cb5442",
    "points": 57350,
    "tx": 2614,
    "sbt": "-",
    "time": "2026-06-22T12:57:57.617933+00:00"
  },
  {
    "rank": 41,
    "address": "0xa7371ada15d2eaf627fdaeb2f20ff0c5ab019336",
    "points": 57200,
    "tx": 2540,
    "sbt": "-",
    "time": "2026-06-22T12:57:57.617940+00:00"
  },
  {
    "rank": 42,
    "address": "0x5f7be1481c3196a06d8edf56cee9d7184335c4dc",
    "points": 57000,
    "tx": 2547,
    "sbt": "-",
    "time": "2026-06-22T12:57:57.617949+00:00"
  },
  {
    "rank": 43,
    "address": "0x3f6caab02be9fc106e2795790dcfab0e861400dc",
    "points": 56900,
    "tx": 2598,
    "sbt": "-",
    "time": "2026-06-22T12:57:57.617958+00:00"
  },
  {
    "rank": 44,
    "address": "0x465f2a9bb8a265c640371681a174f222fbc81737",
    "points": 56900,
    "tx": 2575,
    "sbt": "-",
    "time": "2026-06-22T12:57:57.617965+00:00"
  },
  {
    "rank": 45,
    "address": "0xad541bd2a5004b8fa3dbad936fa1d7c275f9c607",
    "points": 56650,
    "tx": 2591,
    "sbt": "-",
    "time": "2026-06-22T12:57:57.617972+00:00"
  },
  {
    "rank": 46,
    "address": "0xe91cb0ed0d231598521a4d541ef6cddccaadc728",
    "points": 56650,
    "tx": 2559,
    "sbt": "-",
    "time": "2026-06-22T12:57:57.617979+00:00"
  },
  {
    "rank": 47,
    "address": "0x15ed442bc0681490da3ceef23011dcf8e6c4e011",
    "points": 56550,
    "tx": 2433,
    "sbt": "-",
    "time": "2026-06-22T12:57:57.617986+00:00"
  },
  {
    "rank": 48,
    "address": "0xfd54722b91c7f3b1cc3a5f9726b589c7be86bba0",
    "points": 56200,
    "tx": 2540,
    "sbt": "-",
    "time": "2026-06-22T12:57:57.617993+00:00"
  },
  {
    "rank": 49,
    "address": "0x875233377a7781d7803ecb98bb92316e64c24a58",
    "points": 56050,
    "tx": 2569,
    "sbt": "-",
    "time": "2026-06-22T12:57:57.618001+00:00"
  },
  {
    "rank": 50,
    "address": "0xddad0202a7e53cad7ddfd126aebe82cf146affd0",
    "points": 55900,
    "tx": 2528,
    "sbt": "-",
    "time": "2026-06-22T12:57:57.618008+00:00"
  }
]